siphon/__init__.py
siphon/logger.py
siphon/database/__init__.py
siphon/database/aiopostgres.py
siphon/database/config.py
siphon/database/mysql.py
siphon/database/postgres.py
siphon/queue/__init__.py
siphon/queue/aioqueue.py
siphon/queue/types.py
siphon/queue/violations.py
siphon/rabbit/__init__.py
siphon/rabbit/aiorabbit.py
siphon/rabbit/config.py
siphon_data-0.6.1.dist-info/LICENSE
siphon_data-0.6.1.dist-info/METADATA
siphon_data-0.6.1.dist-info/WHEEL
siphon_data-0.6.1.dist-info/entry_points.txt
siphon_data-0.6.1.dist-info/top_level.txt
siphon_data-0.6.1.dist-info/RECORD
